Workbook

Sheet Start here
B2: 1. This workbook does two things: it works out what your money has actually earned, and it shows what it would take to reach a goal.
B4: 2. Save your own copy before you type anything, so you always have a clean one.
B6: 3. On the My investments tab, enter one row for every payment you made: the date, then Money in or Money out from the dropdown, then the amount as a plain positive number.
B8: Dates are shown as dd-mmm-yyyy. If a date you typed reads back as a different day, your computer is set to American dates; retype it and check it reads the way you meant. 4. In the last row, enter today's date, choose Worth today, and type what the holding is worth right now. Your XIRR appears at the top of that tab.
B10: 5. On the Plan my goal tab, enter what you are aiming for, what you already have, and what you invest each month. It shows where you land and what would close the gap.
B12: 6. The Example tab is the same thing already filled in, if you get stuck.

Sheet My investments
A2: Fund name | H2: Your portfolio
H3: You put in | I3: =Calc!$D$3
A4: Your XIRR | B4: =IFERROR(XIRR(Flow_Values,Flow_Dates),IFERROR(XIRR(Flow_Values,Flow_Dates,-0.5),"Check the status line below")) | H4: You took out | I4: =Calc!$D$4
B5: =IF(COUNT($B$8:$B$507)=0,"Add your first investment above.",IF(Calc!$D$1=0,"Add a last row: today's date, Worth today, and what the holding is worth now.",IF(Calc!$D$2=0,"Add at least one investment.",""))) | H5: Worth now | I5: =Calc!$D$5
B6: Type in the cream cells only — everything else is worked out for you. One row for every payment, with no blank rows in between, and the last row must be today's date, Worth today, and what the holding is worth now. | H6: Gain or loss | I6: =Calc!$D$5+Calc!$D$4-Calc!$D$3
B7: Date | C7: What happened | D7: Amount | E7: Used by the sheet | F7: Which holding | H7: How long you have held it | I7: =IF(COUNT($B$8:$B$507)=0,"",TEXT((OFFSET($B$8,COUNT($B$8:$B$507)-1,0)-$B$8)/365.25,"0.0")&" years")
B8: 44652 | C8: Money in | D8: 500000 | E8: =IF($B8="","",IF($C8="Money in",-$D8,$D8))
B9: 45383 | C9: Money out | D9: 200000 | E9: =IF($B9="","",IF($C9="Money in",-$D9,$D9)) | H9: Each holding on its own
B10: 46113 | C10: Worth today | D10: 450000 | E10: =IF($B10="","",IF($C10="Money in",-$D10,$D10)) | H10: Type a holding name | I10: You put in | J10: Its own XIRR
E11: =IF($B11="","",IF($C11="Money in",-$D11,$D11)) | I11: =IF($H11="","",Calc!$L$1) | J11: =IF($H11="","",IFERROR(XIRR(OFFSET(Calc!$AE$8,0,0,COUNT($B$8:$B$507),1),Flow_Dates),IFERROR(XIRR(OFFSET(Calc!$AE$8,0,0,COUNT($B$8:$B$507),1),Flow_Dates,-0.5),"not enough entries")))
E12: =IF($B12="","",IF($C12="Money in",-$D12,$D12)) | I12: =IF($H12="","",Calc!$L$2) | J12: =IF($H12="","",IFERROR(XIRR(OFFSET(Calc!$AF$8,0,0,COUNT($B$8:$B$507),1),Flow_Dates),IFERROR(XIRR(OFFSET(Calc!$AF$8,0,0,COUNT($B$8:$B$507),1),Flow_Dates,-0.5),"not enough entries")))
E13: =IF($B13="","",IF($C13="Money in",-$D13,$D13)) | I13: =IF($H13="","",Calc!$L$3) | J13: =IF($H13="","",IFERROR(XIRR(OFFSET(Calc!$AG$8,0,0,COUNT($B$8:$B$507),1),Flow_Dates),IFERROR(XIRR(OFFSET(Calc!$AG$8,0,0,COUNT($B$8:$B$507),1),Flow_Dates,-0.5),"not enough entries")))
E14: =IF($B14="","",IF($C14="Money in",-$D14,$D14)) | I14: =IF($H14="","",Calc!$L$4) | J14: =IF($H14="","",IFERROR(XIRR(OFFSET(Calc!$AH$8,0,0,COUNT($B$8:$B$507),1),Flow_Dates),IFERROR(XIRR(OFFSET(Calc!$AH$8,0,0,COUNT($B$8:$B$507),1),Flow_Dates,-0.5),"not enough entries")))
E15: =IF($B15="","",IF($C15="Money in",-$D15,$D15)) | I15: =IF($H15="","",Calc!$L$5) | J15: =IF($H15="","",IFERROR(XIRR(OFFSET(Calc!$AI$8,0,0,COUNT($B$8:$B$507),1),Flow_Dates),IFERROR(XIRR(OFFSET(Calc!$AI$8,0,0,COUNT($B$8:$B$507),1),Flow_Dates,-0.5),"not enough entries")))
E16: =IF($B16="","",IF($C16="Money in",-$D16,$D16))
E17: =IF($B17="","",IF($C17="Money in",-$D17,$D17)) | H17: Leave the names blank if you hold only one thing.
E18: =IF($B18="","",IF($C18="Money in",-$D18,$D18)) | H18: Your portfolio XIRR is not the average of these.
E19: =IF($B19="","",IF($C19="Money in",-$D19,$D19)) | H19: It weighs each holding by how much money you actually had in it, and for how long.
E20: =IF($B20="","",IF($C20="Money in",-$D20,$D20))
E21: =IF($B21="","",IF($C21="Money in",-$D21,$D21))
E22: =IF($B22="","",IF($C22="Money in",-$D22,$D22))
E23: =IF($B23="","",IF($C23="Money in",-$D23,$D23))
E24: =IF($B24="","",IF($C24="Money in",-$D24,$D24))
E25: =IF($B25="","",IF($C25="Money in",-$D25,$D25))
E26: =IF($B26="","",IF($C26="Money in",-$D26,$D26))
E27: =IF($B27="","",IF($C27="Money in",-$D27,$D27))
E28: =IF($B28="","",IF($C28="Money in",-$D28,$D28))
E29: =IF($B29="","",IF($C29="Money in",-$D29,$D29))
E30: =IF($B30="","",IF($C30="Money in",-$D30,$D30))
E31: =IF($B31="","",IF($C31="Money in",-$D31,$D31))
... E507: =IF($B507="","",IF($C507="Money in",-$D507,$D507))

Sheet Plan my goal
B1: Plan my goal
A3: What is this for?
A4: Amount you are aiming for | B4: 5000000
A5: What you have already | B5: 400000
A6: Years left | B6: 15
A7: Investing each month now | B7: 10000
A8: Assumed return each year (%) | B8: 10 | C8: An assumption you choose. Nobody can promise it.
A9: Raise the monthly amount each year by (%) | B9: 0
A11: If nothing changes, you reach | B11: =IF(Calc!$G$10=0,"Check the line below",Calc!$G$11+Calc!$G$12)
B12: =IF($B$6="","Enter how many years are left, on the line above.",IF($B$6<=0,"Years left must be more than zero.",IF($B$6>40,"Enter 40 years or less.",IF($B$4="","Enter the amount you are aiming for.",IF($B$4<=0,"The amount you are aiming for must be more than zero.",IF($B$8>30,"A return has to be between 0% and 30%. A higher assumption does not make a plan, it hides one.",IF($B$8<0,"A return has to be between 0% and 30%.",IF($B$9>25,"A step-up has to be between 0% and 25%.",IF($B$9<0,"A step-up has to be between 0% and 25%.","")))))))))
A14: Against your goal | B14: =IF(Calc!$G$10=0,"",IF(Calc!$G$13>0.5,"Short by "&TEXT(Calc!$G$13,"[>=10000000]₹ ##\,##\,##\,##0;[>=100000]₹ ##\,##\,##0;₹ ##,##0"),IF(Calc!$G$13<-0.5,"Covered, with "&TEXT(-Calc!$G$13,"[>=10000000]₹ ##\,##\,##\,##0;[>=100000]₹ ##\,##\,##0;₹ ##,##0")&" to spare","Covered, exactly on target")))
A15: Extra each month to close it | B15: =IF(Calc!$G$10=0,"",Calc!$G$14) | C15: On top of what you already invest each month.
A17: Where that comes from
A18: What you already have, grown | B18: =IF(Calc!$G$10=0,"",Calc!$G$11)
A19: What your monthly investing adds | B19: =IF(Calc!$G$10=0,"",Calc!$G$12)
A20: Your own money paid in over the years | B20: =IF(Calc!$G$10=0,"",Calc!$G$15)
A22: If you did a little more
A23: Scenario | B23: You reach | C23: Against your goal
A24: Carry on exactly as you are | B24: =IF(Calc!$G$10=0,"",Calc!$G$16) | C24: =IF(Calc!$G$10=0,"",IF(Calc!$G$16>=$B$4,"covered, +"&TEXT(Calc!$G$16-$B$4,"[>=10000000]₹ ##\,##\,##\,##0;[>=100000]₹ ##\,##\,##0;₹ ##,##0"),"short by "&TEXT($B$4-Calc!$G$16,"[>=10000000]₹ ##\,##\,##\,##0;[>=100000]₹ ##\,##\,##0;₹ ##,##0")))
A25: Add ₹2,000 a month | B25: =IF(Calc!$G$10=0,"",Calc!$G$17) | C25: =IF(Calc!$G$10=0,"",IF(Calc!$G$17>=$B$4,"covered, +"&TEXT(Calc!$G$17-$B$4,"[>=10000000]₹ ##\,##\,##\,##0;[>=100000]₹ ##\,##\,##0;₹ ##,##0"),"short by "&TEXT($B$4-Calc!$G$17,"[>=10000000]₹ ##\,##\,##\,##0;[>=100000]₹ ##\,##\,##0;₹ ##,##0")))
A26: Add ₹5,000 a month | B26: =IF(Calc!$G$10=0,"",Calc!$G$18) | C26: =IF(Calc!$G$10=0,"",IF(Calc!$G$18>=$B$4,"covered, +"&TEXT(Calc!$G$18-$B$4,"[>=10000000]₹ ##\,##\,##\,##0;[>=100000]₹ ##\,##\,##0;₹ ##,##0"),"short by "&TEXT($B$4-Calc!$G$18,"[>=10000000]₹ ##\,##\,##\,##0;[>=100000]₹ ##\,##\,##0;₹ ##,##0")))
A27: Same amount, raised 10% every year | B27: =IF(Calc!$G$10=0,"",Calc!$G$19) | C27: =IF(Calc!$G$10=0,"",IF(Calc!$G$19>=$B$4,"covered, +"&TEXT(Calc!$G$19-$B$4,"[>=10000000]₹ ##\,##\,##\,##0;[>=100000]₹ ##\,##\,##0;₹ ##,##0"),"short by "&TEXT($B$4-Calc!$G$19,"[>=10000000]₹ ##\,##\,##\,##0;[>=100000]₹ ##\,##\,##0;₹ ##,##0")))
A29: Every line above uses the return you typed in. It is an assumption, not a forecast.
A30: Real markets do not deliver the same return every year, and a run of poor years early on hurts more than the same years late.
A31: Inflation is not deducted, so a goal set in today's rupees will cost more by the time it arrives.

Sheet Example
A2: Fund name | B2: An example, already filled in
A4: Your XIRR | B4: =IFERROR(XIRR($E$8:$E$10,$B$8:$B$10),IFERROR(XIRR($E$8:$E$10,$B$8:$B$10,-0.5),"Check the status line below"))
B6: Type in the cream cells only — everything else is worked out for you. One row for every payment, with no blank rows in between, and the last row must be today's date, Worth today, and what the holding is worth now.
B7: Date | C7: What happened | D7: Amount | E7: Used by the sheet | F7: Which holding
B8: 45292 | C8: Money in | D8: 100000 | E8: =IF($B8="","",IF($C8="Money in",-$D8,$D8))
B9: 45658 | C9: Money in | D9: 100000 | E9: =IF($B9="","",IF($C9="Money in",-$D9,$D9))
B10: 46023 | C10: Worth today | D10: 228000 | E10: =IF($B10="","",IF($C10="Money in",-$D10,$D10))
E11: =IF($B11="","",IF($C11="Money in",-$D11,$D11))
E12: =IF($B12="","",IF($C12="Money in",-$D12,$D12))
E13: =IF($B13="","",IF($C13="Money in",-$D13,$D13))
E14: =IF($B14="","",IF($C14="Money in",-$D14,$D14))
E15: =IF($B15="","",IF($C15="Money in",-$D15,$D15))
E16: =IF($B16="","",IF($C16="Money in",-$D16,$D16))
E17: =IF($B17="","",IF($C17="Money in",-$D17,$D17))
E18: =IF($B18="","",IF($C18="Money in",-$D18,$D18))
E19: =IF($B19="","",IF($C19="Money in",-$D19,$D19))
E20: =IF($B20="","",IF($C20="Money in",-$D20,$D20))
E21: =IF($B21="","",IF($C21="Money in",-$D21,$D21))
E22: =IF($B22="","",IF($C22="Money in",-$D22,$D22))
... E507: =IF($B507="","",IF($C507="Money in",-$D507,$D507))

Sheet About
B2: XIRR Calculator, version 1.3
B4: Built 31-Aug-2026
B6: This is an educational tool for readers. The figure it produces is before exit load and before tax, and it is not investment advice.
B8: Questions: use the channels listed in the book.
B10: The tabs are protected without a password. To adapt this sheet, choose Review, then Unprotect Sheet.
B12: The Plan my goal tab uses a return you type in yourself. It is an assumption, not a forecast, and it is shown before inflation.
B14: No Excel? Upload this file to Google Sheets and it works there too, unchanged.

Sheet Calc
C1: Rows marked Worth today | D1: =SUM($A$8:$A$507) | F1: annual rate r | G1: =IF('Plan my goal'!$B$8="",0,'Plan my goal'!$B$8/100) | K1: holding 1 invested | L1: =SUM(AK$8:AK$507)
C2: Rows marked Money in | D2: =SUM($B$8:$B$507) | F2: monthly rate i | G2: =(1+$G$1)^(1/12)-1 | K2: holding 2 invested | L2: =SUM(AL$8:AL$507)
C3: Total invested | D3: =SUM($AA$8:$AA$507) | F3: one year of 1/month | G3: =IF($G$2=0,12,(((1+$G$2)^12-1)/$G$2)*(1+$G$2)) | K3: holding 3 invested | L3: =SUM(AM$8:AM$507)
C4: Total withdrawn | D4: =SUM($AB$8:$AB$507) | F4: years Y | G4: =IF('Plan my goal'!$B$6="",0,'Plan my goal'!$B$6) | K4: holding 4 invested | L4: =SUM(AN$8:AN$507)
C5: Worth today | D5: =SUM($AC$8:$AC$507) | F5: step-up g | G5: =IF('Plan my goal'!$B$9="",0,'Plan my goal'!$B$9/100) | I5: =IF($G$5>0.1,$G$5,0.1) | K5: holding 5 invested | L5: =SUM(AO$8:AO$507)
F6: ratio x | G6: =(1+$G$5)/(1+$G$1) | I6: =(1+$I$5)/(1+$G$1)
F7: geometric sum S | G7: =IF($G$4<=0,0,IF($G$6=1,$G$4,(1-$G$6^$G$4)/(1-$G$6))) | I7: =IF($G$4<=0,0,IF($I$6=1,$G$4,(1-$I$6^$G$4)/(1-$I$6)))
A8: =IF('My investments'!$C8="Worth today",1,0) | B8: =IF('My investments'!$C8="Money in",1,0) | F8: growth of 1/month | G8: =IF($G$4<=0,0,$G$3*(1+$G$1)^($G$4-1)*$G$7) | I8: =IF($G$4<=0,0,$G$3*(1+$G$1)^($G$4-1)*$I$7) | AA8: =IF('My investments'!$C8="Money in",'My investments'!$D8,0) | AB8: =IF('My investments'!$C8="Money out",'My investments'!$D8,0) | AC8: =IF('My investments'!$C8="Worth today",'My investments'!$D8,0) | AE8: =IF('My investments'!$H$11="",0,IF('My investments'!$F8='My investments'!$H$11,'My investments'!$E8,0)) | AF8: =IF('My investments'!$H$12="",0,IF('My investments'!$F8='My investments'!$H$12,'My investments'!$E8,0)) | AG8: =IF('My investments'!$H$13="",0,IF('My investments'!$F8='My investments'!$H$13,'My investments'!$E8,0)) | AH8: =IF('My investments'!$H$14="",0,IF('My investments'!$F8='My investments'!$H$14,'My investments'!$E8,0)) | AI8: =IF('My investments'!$H$15="",0,IF('My investments'!$F8='My investments'!$H$15,'My investments'!$E8,0)) | AK8: =IF('My investments'!$H$11="",0,IF('My investments'!$F8='My investments'!$H$11,$AA8,0)) | AL8: =IF('My investments'!$H$12="",0,IF('My investments'!$F8='My investments'!$H$12,$AA8,0)) | AM8: =IF('My investments'!$H$13="",0,IF('My investments'!$F8='My investments'!$H$13,$AA8,0)) | AN8: =IF('My investments'!$H$14="",0,IF('My investments'!$F8='My investments'!$H$14,$AA8,0)) | AO8: =IF('My investments'!$H$15="",0,IF('My investments'!$F8='My investments'!$H$15,$AA8,0))
A9: =IF('My investments'!$C9="Worth today",1,0) | B9: =IF('My investments'!$C9="Money in",1,0) | AA9: =IF('My investments'!$C9="Money in",'My investments'!$D9,0) | AB9: =IF('My investments'!$C9="Money out",'My investments'!$D9,0) | AC9: =IF('My investments'!$C9="Worth today",'My investments'!$D9,0) | AE9: =IF('My investments'!$H$11="",0,IF('My investments'!$F9='My investments'!$H$11,'My investments'!$E9,0)) | AF9: =IF('My investments'!$H$12="",0,IF('My investments'!$F9='My investments'!$H$12,'My investments'!$E9,0)) | AG9: =IF('My investments'!$H$13="",0,IF('My investments'!$F9='My investments'!$H$13,'My investments'!$E9,0)) | AH9: =IF('My investments'!$H$14="",0,IF('My investments'!$F9='My investments'!$H$14,'My investments'!$E9,0)) | AI9: =IF('My investments'!$H$15="",0,IF('My investments'!$F9='My investments'!$H$15,'My investments'!$E9,0)) | AK9: =IF('My investments'!$H$11="",0,IF('My investments'!$F9='My investments'!$H$11,$AA9,0)) | AL9: =IF('My investments'!$H$12="",0,IF('My investments'!$F9='My investments'!$H$12,$AA9,0)) | AM9: =IF('My investments'!$H$13="",0,IF('My investments'!$F9='My investments'!$H$13,$AA9,0)) | AN9: =IF('My investments'!$H$14="",0,IF('My investments'!$F9='My investments'!$H$14,$AA9,0)) | AO9: =IF('My investments'!$H$15="",0,IF('My investments'!$F9='My investments'!$H$15,$AA9,0))
A10: =IF('My investments'!$C10="Worth today",1,0) | B10: =IF('My investments'!$C10="Money in",1,0) | F10: inputs usable? | G10: =IF('Plan my goal'!$B$6="",0,IF('Plan my goal'!$B$6<=0,0,IF('Plan my goal'!$B$6>40,0,IF('Plan my goal'!$B$4="",0,IF('Plan my goal'!$B$4<=0,0,IF('Plan my goal'!$B$8>30,0,IF('Plan my goal'!$B$8<0,0,IF('Plan my goal'!$B$9>25,0,IF('Plan my goal'!$B$9<0,0,1))))))))) | AA10: =IF('My investments'!$C10="Money in",'My investments'!$D10,0) | AB10: =IF('My investments'!$C10="Money out",'My investments'!$D10,0) | AC10: =IF('My investments'!$C10="Worth today",'My investments'!$D10,0) | AE10: =IF('My investments'!$H$11="",0,IF('My investments'!$F10='My investments'!$H$11,'My investments'!$E10,0)) | AF10: =IF('My investments'!$H$12="",0,IF('My investments'!$F10='My investments'!$H$12,'My investments'!$E10,0)) | AG10: =IF('My investments'!$H$13="",0,IF('My investments'!$F10='My investments'!$H$13,'My investments'!$E10,0)) | AH10: =IF('My investments'!$H$14="",0,IF('My investments'!$F10='My investments'!$H$14,'My investments'!$E10,0)) | AI10: =IF('My investments'!$H$15="",0,IF('My investments'!$F10='My investments'!$H$15,'My investments'!$E10,0)) | AK10: =IF('My investments'!$H$11="",0,IF('My investments'!$F10='My investments'!$H$11,$AA10,0)) | AL10: =IF('My investments'!$H$12="",0,IF('My investments'!$F10='My investments'!$H$12,$AA10,0)) | AM10: =IF('My investments'!$H$13="",0,IF('My investments'!$F10='My investments'!$H$13,$AA10,0)) | AN10: =IF('My investments'!$H$14="",0,IF('My investments'!$F10='My investments'!$H$14,$AA10,0)) | AO10: =IF('My investments'!$H$15="",0,IF('My investments'!$F10='My investments'!$H$15,$AA10,0))
A11: =IF('My investments'!$C11="Worth today",1,0) | B11: =IF('My investments'!$C11="Money in",1,0) | F11: from what you have | G11: =IF('Plan my goal'!$B$5="",0,'Plan my goal'!$B$5)*(1+$G$1)^$G$4 | AA11: =IF('My investments'!$C11="Money in",'My investments'!$D11,0) | AB11: =IF('My investments'!$C11="Money out",'My investments'!$D11,0) | AC11: =IF('My investments'!$C11="Worth today",'My investments'!$D11,0) | AE11: =IF('My investments'!$H$11="",0,IF('My investments'!$F11='My investments'!$H$11,'My investments'!$E11,0)) | AF11: =IF('My investments'!$H$12="",0,IF('My investments'!$F11='My investments'!$H$12,'My investments'!$E11,0)) | AG11: =IF('My investments'!$H$13="",0,IF('My investments'!$F11='My investments'!$H$13,'My investments'!$E11,0)) | AH11: =IF('My investments'!$H$14="",0,IF('My investments'!$F11='My investments'!$H$14,'My investments'!$E11,0)) | AI11: =IF('My investments'!$H$15="",0,IF('My investments'!$F11='My investments'!$H$15,'My investments'!$E11,0)) | AK11: =IF('My investments'!$H$11="",0,IF('My investments'!$F11='My investments'!$H$11,$AA11,0)) | AL11: =IF('My investments'!$H$12="",0,IF('My investments'!$F11='My investments'!$H$12,$AA11,0)) | AM11: =IF('My investments'!$H$13="",0,IF('My investments'!$F11='My investments'!$H$13,$AA11,0)) | AN11: =IF('My investments'!$H$14="",0,IF('My investments'!$F11='My investments'!$H$14,$AA11,0)) | AO11: =IF('My investments'!$H$15="",0,IF('My investments'!$F11='My investments'!$H$15,$AA11,0))
A12: =IF('My investments'!$C12="Worth today",1,0) | B12: =IF('My investments'!$C12="Money in",1,0) | F12: from monthly | G12: =IF('Plan my goal'!$B$7="",0,'Plan my goal'!$B$7)*$G$8 | AA12: =IF('My investments'!$C12="Money in",'My investments'!$D12,0) | AB12: =IF('My investments'!$C12="Money out",'My investments'!$D12,0) | AC12: =IF('My investments'!$C12="Worth today",'My investments'!$D12,0) | AE12: =IF('My investments'!$H$11="",0,IF('My investments'!$F12='My investments'!$H$11,'My investments'!$E12,0)) | AF12: =IF('My investments'!$H$12="",0,IF('My investments'!$F12='My investments'!$H$12,'My investments'!$E12,0)) | AG12: =IF('My investments'!$H$13="",0,IF('My investments'!$F12='My investments'!$H$13,'My investments'!$E12,0)) | AH12: =IF('My investments'!$H$14="",0,IF('My investments'!$F12='My investments'!$H$14,'My investments'!$E12,0)) | AI12: =IF('My investments'!$H$15="",0,IF('My investments'!$F12='My investments'!$H$15,'My investments'!$E12,0)) | AK12: =IF('My investments'!$H$11="",0,IF('My investments'!$F12='My investments'!$H$11,$AA12,0)) | AL12: =IF('My investments'!$H$12="",0,IF('My investments'!$F12='My investments'!$H$12,$AA12,0)) | AM12: =IF('My investments'!$H$13="",0,IF('My investments'!$F12='My investments'!$H$13,$AA12,0)) | AN12: =IF('My investments'!$H$14="",0,IF('My investments'!$F12='My investments'!$H$14,$AA12,0)) | AO12: =IF('My investments'!$H$15="",0,IF('My investments'!$F12='My investments'!$H$15,$AA12,0))
A13: =IF('My investments'!$C13="Worth today",1,0) | B13: =IF('My investments'!$C13="Money in",1,0) | F13: gap | G13: =IF('Plan my goal'!$B$4="",0,'Plan my goal'!$B$4)-($G$11+$G$12) | AA13: =IF('My investments'!$C13="Money in",'My investments'!$D13,0) | AB13: =IF('My investments'!$C13="Money out",'My investments'!$D13,0) | AC13: =IF('My investments'!$C13="Worth today",'My investments'!$D13,0) | AE13: =IF('My investments'!$H$11="",0,IF('My investments'!$F13='My investments'!$H$11,'My investments'!$E13,0)) | AF13: =IF('My investments'!$H$12="",0,IF('My investments'!$F13='My investments'!$H$12,'My investments'!$E13,0)) | AG13: =IF('My investments'!$H$13="",0,IF('My investments'!$F13='My investments'!$H$13,'My investments'!$E13,0)) | AH13: =IF('My investments'!$H$14="",0,IF('My investments'!$F13='My investments'!$H$14,'My investments'!$E13,0)) | AI13: =IF('My investments'!$H$15="",0,IF('My investments'!$F13='My investments'!$H$15,'My investments'!$E13,0)) | AK13: =IF('My investments'!$H$11="",0,IF('My investments'!$F13='My investments'!$H$11,$AA13,0)) | AL13: =IF('My investments'!$H$12="",0,IF('My investments'!$F13='My investments'!$H$12,$AA13,0)) | AM13: =IF('My investments'!$H$13="",0,IF('My investments'!$F13='My investments'!$H$13,$AA13,0)) | AN13: =IF('My investments'!$H$14="",0,IF('My investments'!$F13='My investments'!$H$14,$AA13,0)) | AO13: =IF('My investments'!$H$15="",0,IF('My investments'!$F13='My investments'!$H$15,$AA13,0))
A14: =IF('My investments'!$C14="Worth today",1,0) | B14: =IF('My investments'!$C14="Money in",1,0) | F14: extra each month | G14: =IF($G$13<=0.5,0,IF($G$8<=0,0,$G$13/$G$8)) | AA14: =IF('My investments'!$C14="Money in",'My investments'!$D14,0) | AB14: =IF('My investments'!$C14="Money out",'My investments'!$D14,0) | AC14: =IF('My investments'!$C14="Worth today",'My investments'!$D14,0) | AE14: =IF('My investments'!$H$11="",0,IF('My investments'!$F14='My investments'!$H$11,'My investments'!$E14,0)) | AF14: =IF('My investments'!$H$12="",0,IF('My investments'!$F14='My investments'!$H$12,'My investments'!$E14,0)) | AG14: =IF('My investments'!$H$13="",0,IF('My investments'!$F14='My investments'!$H$13,'My investments'!$E14,0)) | AH14: =IF('My investments'!$H$14="",0,IF('My investments'!$F14='My investments'!$H$14,'My investments'!$E14,0)) | AI14: =IF('My investments'!$H$15="",0,IF('My investments'!$F14='My investments'!$H$15,'My investments'!$E14,0)) | AK14: =IF('My investments'!$H$11="",0,IF('My investments'!$F14='My investments'!$H$11,$AA14,0)) | AL14: =IF('My investments'!$H$12="",0,IF('My investments'!$F14='My investments'!$H$12,$AA14,0)) | AM14: =IF('My investments'!$H$13="",0,IF('My investments'!$F14='My investments'!$H$13,$AA14,0)) | AN14: =IF('My investments'!$H$14="",0,IF('My investments'!$F14='My investments'!$H$14,$AA14,0)) | AO14: =IF('My investments'!$H$15="",0,IF('My investments'!$F14='My investments'!$H$15,$AA14,0))
A15: =IF('My investments'!$C15="Worth today",1,0) | B15: =IF('My investments'!$C15="Money in",1,0) | F15: own money paid in | G15: =IF('Plan my goal'!$B$7="",0,'Plan my goal'!$B$7)*12*$G$20 | AA15: =IF('My investments'!$C15="Money in",'My investments'!$D15,0) | AB15: =IF('My investments'!$C15="Money out",'My investments'!$D15,0) | AC15: =IF('My investments'!$C15="Worth today",'My investments'!$D15,0) | AE15: =IF('My investments'!$H$11="",0,IF('My investments'!$F15='My investments'!$H$11,'My investments'!$E15,0)) | AF15: =IF('My investments'!$H$12="",0,IF('My investments'!$F15='My investments'!$H$12,'My investments'!$E15,0)) | AG15: =IF('My investments'!$H$13="",0,IF('My investments'!$F15='My investments'!$H$13,'My investments'!$E15,0)) | AH15: =IF('My investments'!$H$14="",0,IF('My investments'!$F15='My investments'!$H$14,'My investments'!$E15,0)) | AI15: =IF('My investments'!$H$15="",0,IF('My investments'!$F15='My investments'!$H$15,'My investments'!$E15,0)) | AK15: =IF('My investments'!$H$11="",0,IF('My investments'!$F15='My investments'!$H$11,$AA15,0)) | AL15: =IF('My investments'!$H$12="",0,IF('My investments'!$F15='My investments'!$H$12,$AA15,0)) | AM15: =IF('My investments'!$H$13="",0,IF('My investments'!$F15='My investments'!$H$13,$AA15,0)) | AN15: =IF('My investments'!$H$14="",0,IF('My investments'!$F15='My investments'!$H$14,$AA15,0)) | AO15: =IF('My investments'!$H$15="",0,IF('My investments'!$F15='My investments'!$H$15,$AA15,0))
A16: =IF('My investments'!$C16="Worth today",1,0) | B16: =IF('My investments'!$C16="Money in",1,0) | F16: as you are | G16: =$G$11+$G$12 | AA16: =IF('My investments'!$C16="Money in",'My investments'!$D16,0) | AB16: =IF('My investments'!$C16="Money out",'My investments'!$D16,0) | AC16: =IF('My investments'!$C16="Worth today",'My investments'!$D16,0) | AE16: =IF('My investments'!$H$11="",0,IF('My investments'!$F16='My investments'!$H$11,'My investments'!$E16,0)) | AF16: =IF('My investments'!$H$12="",0,IF('My investments'!$F16='My investments'!$H$12,'My investments'!$E16,0)) | AG16: =IF('My investments'!$H$13="",0,IF('My investments'!$F16='My investments'!$H$13,'My investments'!$E16,0)) | AH16: =IF('My investments'!$H$14="",0,IF('My investments'!$F16='My investments'!$H$14,'My investments'!$E16,0)) | AI16: =IF('My investments'!$H$15="",0,IF('My investments'!$F16='My investments'!$H$15,'My investments'!$E16,0)) | AK16: =IF('My investments'!$H$11="",0,IF('My investments'!$F16='My investments'!$H$11,$AA16,0)) | AL16: =IF('My investments'!$H$12="",0,IF('My investments'!$F16='My investments'!$H$12,$AA16,0)) | AM16: =IF('My investments'!$H$13="",0,IF('My investments'!$F16='My investments'!$H$13,$AA16,0)) | AN16: =IF('My investments'!$H$14="",0,IF('My investments'!$F16='My investments'!$H$14,$AA16,0)) | AO16: =IF('My investments'!$H$15="",0,IF('My investments'!$F16='My investments'!$H$15,$AA16,0))
A17: =IF('My investments'!$C17="Worth today",1,0) | B17: =IF('My investments'!$C17="Money in",1,0) | F17: plus 2,000 | G17: =$G$11+(IF('Plan my goal'!$B$7="",0,'Plan my goal'!$B$7)+2000)*$G$8 | AA17: =IF('My investments'!$C17="Money in",'My investments'!$D17,0) | AB17: =IF('My investments'!$C17="Money out",'My investments'!$D17,0) | AC17: =IF('My investments'!$C17="Worth today",'My investments'!$D17,0) | AE17: =IF('My investments'!$H$11="",0,IF('My investments'!$F17='My investments'!$H$11,'My investments'!$E17,0)) | AF17: =IF('My investments'!$H$12="",0,IF('My investments'!$F17='My investments'!$H$12,'My investments'!$E17,0)) | AG17: =IF('My investments'!$H$13="",0,IF('My investments'!$F17='My investments'!$H$13,'My investments'!$E17,0)) | AH17: =IF('My investments'!$H$14="",0,IF('My investments'!$F17='My investments'!$H$14,'My investments'!$E17,0)) | AI17: =IF('My investments'!$H$15="",0,IF('My investments'!$F17='My investments'!$H$15,'My investments'!$E17,0)) | AK17: =IF('My investments'!$H$11="",0,IF('My investments'!$F17='My investments'!$H$11,$AA17,0)) | AL17: =IF('My investments'!$H$12="",0,IF('My investments'!$F17='My investments'!$H$12,$AA17,0)) | AM17: =IF('My investments'!$H$13="",0,IF('My investments'!$F17='My investments'!$H$13,$AA17,0)) | AN17: =IF('My investments'!$H$14="",0,IF('My investments'!$F17='My investments'!$H$14,$AA17,0)) | AO17: =IF('My investments'!$H$15="",0,IF('My investments'!$F17='My investments'!$H$15,$AA17,0))
A18: =IF('My investments'!$C18="Worth today",1,0) | B18: =IF('My investments'!$C18="Money in",1,0) | F18: plus 5,000 | G18: =$G$11+(IF('Plan my goal'!$B$7="",0,'Plan my goal'!$B$7)+5000)*$G$8 | AA18: =IF('My investments'!$C18="Money in",'My investments'!$D18,0) | AB18: =IF('My investments'!$C18="Money out",'My investments'!$D18,0) | AC18: =IF('My investments'!$C18="Worth today",'My investments'!$D18,0) | AE18: =IF('My investments'!$H$11="",0,IF('My investments'!$F18='My investments'!$H$11,'My investments'!$E18,0)) | AF18: =IF('My investments'!$H$12="",0,IF('My investments'!$F18='My investments'!$H$12,'My investments'!$E18,0)) | AG18: =IF('My investments'!$H$13="",0,IF('My investments'!$F18='My investments'!$H$13,'My investments'!$E18,0)) | AH18: =IF('My investments'!$H$14="",0,IF('My investments'!$F18='My investments'!$H$14,'My investments'!$E18,0)) | AI18: =IF('My investments'!$H$15="",0,IF('My investments'!$F18='My investments'!$H$15,'My investments'!$E18,0)) | AK18: =IF('My investments'!$H$11="",0,IF('My investments'!$F18='My investments'!$H$11,$AA18,0)) | AL18: =IF('My investments'!$H$12="",0,IF('My investments'!$F18='My investments'!$H$12,$AA18,0)) | AM18: =IF('My investments'!$H$13="",0,IF('My investments'!$F18='My investments'!$H$13,$AA18,0)) | AN18: =IF('My investments'!$H$14="",0,IF('My investments'!$F18='My investments'!$H$14,$AA18,0)) | AO18: =IF('My investments'!$H$15="",0,IF('My investments'!$F18='My investments'!$H$15,$AA18,0))
A19: =IF('My investments'!$C19="Worth today",1,0) | B19: =IF('My investments'!$C19="Money in",1,0) | F19: raised 10% a year | G19: =$G$11+IF('Plan my goal'!$B$7="",0,'Plan my goal'!$B$7)*$I$8 | AA19: =IF('My investments'!$C19="Money in",'My investments'!$D19,0) | AB19: =IF('My investments'!$C19="Money out",'My investments'!$D19,0) | AC19: =IF('My investments'!$C19="Worth today",'My investments'!$D19,0) | AE19: =IF('My investments'!$H$11="",0,IF('My investments'!$F19='My investments'!$H$11,'My investments'!$E19,0)) | AF19: =IF('My investments'!$H$12="",0,IF('My investments'!$F19='My investments'!$H$12,'My investments'!$E19,0)) | AG19: =IF('My investments'!$H$13="",0,IF('My investments'!$F19='My investments'!$H$13,'My investments'!$E19,0)) | AH19: =IF('My investments'!$H$14="",0,IF('My investments'!$F19='My investments'!$H$14,'My investments'!$E19,0)) | AI19: =IF('My investments'!$H$15="",0,IF('My investments'!$F19='My investments'!$H$15,'My investments'!$E19,0)) | AK19: =IF('My investments'!$H$11="",0,IF('My investments'!$F19='My investments'!$H$11,$AA19,0)) | AL19: =IF('My investments'!$H$12="",0,IF('My investments'!$F19='My investments'!$H$12,$AA19,0)) | AM19: =IF('My investments'!$H$13="",0,IF('My investments'!$F19='My investments'!$H$13,$AA19,0)) | AN19: =IF('My investments'!$H$14="",0,IF('My investments'!$F19='My investments'!$H$14,$AA19,0)) | AO19: =IF('My investments'!$H$15="",0,IF('My investments'!$F19='My investments'!$H$15,$AA19,0))
A20: =IF('My investments'!$C20="Worth today",1,0) | B20: =IF('My investments'!$C20="Money in",1,0) | F20: step-up sum T | G20: =IF($G$4<=0,0,IF($G$5=0,$G$4,((1+$G$5)^$G$4-1)/$G$5)) | AA20: =IF('My investments'!$C20="Money in",'My investments'!$D20,0) | AB20: =IF('My investments'!$C20="Money out",'My investments'!$D20,0) | AC20: =IF('My investments'!$C20="Worth today",'My investments'!$D20,0) | AE20: =IF('My investments'!$H$11="",0,IF('My investments'!$F20='My investments'!$H$11,'My investments'!$E20,0)) | AF20: =IF('My investments'!$H$12="",0,IF('My investments'!$F20='My investments'!$H$12,'My investments'!$E20,0)) | AG20: =IF('My investments'!$H$13="",0,IF('My investments'!$F20='My investments'!$H$13,'My investments'!$E20,0)) | AH20: =IF('My investments'!$H$14="",0,IF('My investments'!$F20='My investments'!$H$14,'My investments'!$E20,0)) | AI20: =IF('My investments'!$H$15="",0,IF('My investments'!$F20='My investments'!$H$15,'My investments'!$E20,0)) | AK20: =IF('My investments'!$H$11="",0,IF('My investments'!$F20='My investments'!$H$11,$AA20,0)) | AL20: =IF('My investments'!$H$12="",0,IF('My investments'!$F20='My investments'!$H$12,$AA20,0)) | AM20: =IF('My investments'!$H$13="",0,IF('My investments'!$F20='My investments'!$H$13,$AA20,0)) | AN20: =IF('My investments'!$H$14="",0,IF('My investments'!$F20='My investments'!$H$14,$AA20,0)) | AO20: =IF('My investments'!$H$15="",0,IF('My investments'!$F20='My investments'!$H$15,$AA20,0))
A21: =IF('My investments'!$C21="Worth today",1,0) | B21: =IF('My investments'!$C21="Money in",1,0) | AA21: =IF('My investments'!$C21="Money in",'My investments'!$D21,0) | AB21: =IF('My investments'!$C21="Money out",'My investments'!$D21,0) | AC21: =IF('My investments'!$C21="Worth today",'My investments'!$D21,0) | AE21: =IF('My investments'!$H$11="",0,IF('My investments'!$F21='My investments'!$H$11,'My investments'!$E21,0)) | AF21: =IF('My investments'!$H$12="",0,IF('My investments'!$F21='My investments'!$H$12,'My investments'!$E21,0)) | AG21: =IF('My investments'!$H$13="",0,IF('My investments'!$F21='My investments'!$H$13,'My investments'!$E21,0)) | AH21: =IF('My investments'!$H$14="",0,IF('My investments'!$F21='My investments'!$H$14,'My investments'!$E21,0)) | AI21: =IF('My investments'!$H$15="",0,IF('My investments'!$F21='My investments'!$H$15,'My investments'!$E21,0)) | AK21: =IF('My investments'!$H$11="",0,IF('My investments'!$F21='My investments'!$H$11,$AA21,0)) | AL21: =IF('My investments'!$H$12="",0,IF('My investments'!$F21='My investments'!$H$12,$AA21,0)) | AM21: =IF('My investments'!$H$13="",0,IF('My investments'!$F21='My investments'!$H$13,$AA21,0)) | AN21: =IF('My investments'!$H$14="",0,IF('My investments'!$F21='My investments'!$H$14,$AA21,0)) | AO21: =IF('My investments'!$H$15="",0,IF('My investments'!$F21='My investments'!$H$15,$AA21,0))
A22: =IF('My investments'!$C22="Worth today",1,0) | B22: =IF('My investments'!$C22="Money in",1,0) | AA22: =IF('My investments'!$C22="Money in",'My investments'!$D22,0) | AB22: =IF('My investments'!$C22="Money out",'My investments'!$D22,0) | AC22: =IF('My investments'!$C22="Worth today",'My investments'!$D22,0) | AE22: =IF('My investments'!$H$11="",0,IF('My investments'!$F22='My investments'!$H$11,'My investments'!$E22,0)) | AF22: =IF('My investments'!$H$12="",0,IF('My investments'!$F22='My investments'!$H$12,'My investments'!$E22,0)) | AG22: =IF('My investments'!$H$13="",0,IF('My investments'!$F22='My investments'!$H$13,'My investments'!$E22,0)) | AH22: =IF('My investments'!$H$14="",0,IF('My investments'!$F22='My investments'!$H$14,'My investments'!$E22,0)) | AI22: =IF('My investments'!$H$15="",0,IF('My investments'!$F22='My investments'!$H$15,'My investments'!$E22,0)) | AK22: =IF('My investments'!$H$11="",0,IF('My investments'!$F22='My investments'!$H$11,$AA22,0)) | AL22: =IF('My investments'!$H$12="",0,IF('My investments'!$F22='My investments'!$H$12,$AA22,0)) | AM22: =IF('My investments'!$H$13="",0,IF('My investments'!$F22='My investments'!$H$13,$AA22,0)) | AN22: =IF('My investments'!$H$14="",0,IF('My investments'!$F22='My investments'!$H$14,$AA22,0)) | AO22: =IF('My investments'!$H$15="",0,IF('My investments'!$F22='My investments'!$H$15,$AA22,0))
A23: =IF('My investments'!$C23="Worth today",1,0) | B23: =IF('My investments'!$C23="Money in",1,0) | AA23: =IF('My investments'!$C23="Money in",'My investments'!$D23,0) | AB23: =IF('My investments'!$C23="Money out",'My investments'!$D23,0) | AC23: =IF('My investments'!$C23="Worth today",'My investments'!$D23,0) | AE23: =IF('My investments'!$H$11="",0,IF('My investments'!$F23='My investments'!$H$11,'My investments'!$E23,0)) | AF23: =IF('My investments'!$H$12="",0,IF('My investments'!$F23='My investments'!$H$12,'My investments'!$E23,0)) | AG23: =IF('My investments'!$H$13="",0,IF('My investments'!$F23='My investments'!$H$13,'My investments'!$E23,0)) | AH23: =IF('My investments'!$H$14="",0,IF('My investments'!$F23='My investments'!$H$14,'My investments'!$E23,0)) | AI23: =IF('My investments'!$H$15="",0,IF('My investments'!$F23='My investments'!$H$15,'My investments'!$E23,0)) | AK23: =IF('My investments'!$H$11="",0,IF('My investments'!$F23='My investments'!$H$11,$AA23,0)) | AL23: =IF('My investments'!$H$12="",0,IF('My investments'!$F23='My investments'!$H$12,$AA23,0)) | AM23: =IF('My investments'!$H$13="",0,IF('My investments'!$F23='My investments'!$H$13,$AA23,0)) | AN23: =IF('My investments'!$H$14="",0,IF('My investments'!$F23='My investments'!$H$14,$AA23,0)) | AO23: =IF('My investments'!$H$15="",0,IF('My investments'!$F23='My investments'!$H$15,$AA23,0))
A24: =IF('My investments'!$C24="Worth today",1,0) | B24: =IF('My investments'!$C24="Money in",1,0) | AA24: =IF('My investments'!$C24="Money in",'My investments'!$D24,0) | AB24: =IF('My investments'!$C24="Money out",'My investments'!$D24,0) | AC24: =IF('My investments'!$C24="Worth today",'My investments'!$D24,0) | AE24: =IF('My investments'!$H$11="",0,IF('My investments'!$F24='My investments'!$H$11,'My investments'!$E24,0)) | AF24: =IF('My investments'!$H$12="",0,IF('My investments'!$F24='My investments'!$H$12,'My investments'!$E24,0)) | AG24: =IF('My investments'!$H$13="",0,IF('My investments'!$F24='My investments'!$H$13,'My investments'!$E24,0)) | AH24: =IF('My investments'!$H$14="",0,IF('My investments'!$F24='My investments'!$H$14,'My investments'!$E24,0)) | AI24: =IF('My investments'!$H$15="",0,IF('My investments'!$F24='My investments'!$H$15,'My investments'!$E24,0)) | AK24: =IF('My investments'!$H$11="",0,IF('My investments'!$F24='My investments'!$H$11,$AA24,0)) | AL24: =IF('My investments'!$H$12="",0,IF('My investments'!$F24='My investments'!$H$12,$AA24,0)) | AM24: =IF('My investments'!$H$13="",0,IF('My investments'!$F24='My investments'!$H$13,$AA24,0)) | AN24: =IF('My investments'!$H$14="",0,IF('My investments'!$F24='My investments'!$H$14,$AA24,0)) | AO24: =IF('My investments'!$H$15="",0,IF('My investments'!$F24='My investments'!$H$15,$AA24,0))
A25: =IF('My investments'!$C25="Worth today",1,0) | B25: =IF('My investments'!$C25="Money in",1,0) | AA25: =IF('My investments'!$C25="Money in",'My investments'!$D25,0) | AB25: =IF('My investments'!$C25="Money out",'My investments'!$D25,0) | AC25: =IF('My investments'!$C25="Worth today",'My investments'!$D25,0) | AE25: =IF('My investments'!$H$11="",0,IF('My investments'!$F25='My investments'!$H$11,'My investments'!$E25,0)) | AF25: =IF('My investments'!$H$12="",0,IF('My investments'!$F25='My investments'!$H$12,'My investments'!$E25,0)) | AG25: =IF('My investments'!$H$13="",0,IF('My investments'!$F25='My investments'!$H$13,'My investments'!$E25,0)) | AH25: =IF('My investments'!$H$14="",0,IF('My investments'!$F25='My investments'!$H$14,'My investments'!$E25,0)) | AI25: =IF('My investments'!$H$15="",0,IF('My investments'!$F25='My investments'!$H$15,'My investments'!$E25,0)) | AK25: =IF('My investments'!$H$11="",0,IF('My investments'!$F25='My investments'!$H$11,$AA25,0)) | AL25: =IF('My investments'!$H$12="",0,IF('My investments'!$F25='My investments'!$H$12,$AA25,0)) | AM25: =IF('My investments'!$H$13="",0,IF('My investments'!$F25='My investments'!$H$13,$AA25,0)) | AN25: =IF('My investments'!$H$14="",0,IF('My investments'!$F25='My investments'!$H$14,$AA25,0)) | AO25: =IF('My investments'!$H$15="",0,IF('My investments'!$F25='My investments'!$H$15,$AA25,0))
A26: =IF('My investments'!$C26="Worth today",1,0) | B26: =IF('My investments'!$C26="Money in",1,0) | AA26: =IF('My investments'!$C26="Money in",'My investments'!$D26,0) | AB26: =IF('My investments'!$C26="Money out",'My investments'!$D26,0) | AC26: =IF('My investments'!$C26="Worth today",'My investments'!$D26,0) | AE26: =IF('My investments'!$H$11="",0,IF('My investments'!$F26='My investments'!$H$11,'My investments'!$E26,0)) | AF26: =IF('My investments'!$H$12="",0,IF('My investments'!$F26='My investments'!$H$12,'My investments'!$E26,0)) | AG26: =IF('My investments'!$H$13="",0,IF('My investments'!$F26='My investments'!$H$13,'My investments'!$E26,0)) | AH26: =IF('My investments'!$H$14="",0,IF('My investments'!$F26='My investments'!$H$14,'My investments'!$E26,0)) | AI26: =IF('My investments'!$H$15="",0,IF('My investments'!$F26='My investments'!$H$15,'My investments'!$E26,0)) | AK26: =IF('My investments'!$H$11="",0,IF('My investments'!$F26='My investments'!$H$11,$AA26,0)) | AL26: =IF('My investments'!$H$12="",0,IF('My investments'!$F26='My investments'!$H$12,$AA26,0)) | AM26: =IF('My investments'!$H$13="",0,IF('My investments'!$F26='My investments'!$H$13,$AA26,0)) | AN26: =IF('My investments'!$H$14="",0,IF('My investments'!$F26='My investments'!$H$14,$AA26,0)) | AO26: =IF('My investments'!$H$15="",0,IF('My investments'!$F26='My investments'!$H$15,$AA26,0))
A27: =IF('My investments'!$C27="Worth today",1,0) | B27: =IF('My investments'!$C27="Money in",1,0) | AA27: =IF('My investments'!$C27="Money in",'My investments'!$D27,0) | AB27: =IF('My investments'!$C27="Money out",'My investments'!$D27,0) | AC27: =IF('My investments'!$C27="Worth today",'My investments'!$D27,0) | AE27: =IF('My investments'!$H$11="",0,IF('My investments'!$F27='My investments'!$H$11,'My investments'!$E27,0)) | AF27: =IF('My investments'!$H$12="",0,IF('My investments'!$F27='My investments'!$H$12,'My investments'!$E27,0)) | AG27: =IF('My investments'!$H$13="",0,IF('My investments'!$F27='My investments'!$H$13,'My investments'!$E27,0)) | AH27: =IF('My investments'!$H$14="",0,IF('My investments'!$F27='My investments'!$H$14,'My investments'!$E27,0)) | AI27: =IF('My investments'!$H$15="",0,IF('My investments'!$F27='My investments'!$H$15,'My investments'!$E27,0)) | AK27: =IF('My investments'!$H$11="",0,IF('My investments'!$F27='My investments'!$H$11,$AA27,0)) | AL27: =IF('My investments'!$H$12="",0,IF('My investments'!$F27='My investments'!$H$12,$AA27,0)) | AM27: =IF('My investments'!$H$13="",0,IF('My investments'!$F27='My investments'!$H$13,$AA27,0)) | AN27: =IF('My investments'!$H$14="",0,IF('My investments'!$F27='My investments'!$H$14,$AA27,0)) | AO27: =IF('My investments'!$H$15="",0,IF('My investments'!$F27='My investments'!$H$15,$AA27,0))
A28: =IF('My investments'!$C28="Worth today",1,0) | B28: =IF('My investments'!$C28="Money in",1,0) | AA28: =IF('My investments'!$C28="Money in",'My investments'!$D28,0) | AB28: =IF('My investments'!$C28="Money out",'My investments'!$D28,0) | AC28: =IF('My investments'!$C28="Worth today",'My investments'!$D28,0) | AE28: =IF('My investments'!$H$11="",0,IF('My investments'!$F28='My investments'!$H$11,'My investments'!$E28,0)) | AF28: =IF('My investments'!$H$12="",0,IF('My investments'!$F28='My investments'!$H$12,'My investments'!$E28,0)) | AG28: =IF('My investments'!$H$13="",0,IF('My investments'!$F28='My investments'!$H$13,'My investments'!$E28,0)) | AH28: =IF('My investments'!$H$14="",0,IF('My investments'!$F28='My investments'!$H$14,'My investments'!$E28,0)) | AI28: =IF('My investments'!$H$15="",0,IF('My investments'!$F28='My investments'!$H$15,'My investments'!$E28,0)) | AK28: =IF('My investments'!$H$11="",0,IF('My investments'!$F28='My investments'!$H$11,$AA28,0)) | AL28: =IF('My investments'!$H$12="",0,IF('My investments'!$F28='My investments'!$H$12,$AA28,0)) | AM28: =IF('My investments'!$H$13="",0,IF('My investments'!$F28='My investments'!$H$13,$AA28,0)) | AN28: =IF('My investments'!$H$14="",0,IF('My investments'!$F28='My investments'!$H$14,$AA28,0)) | AO28: =IF('My investments'!$H$15="",0,IF('My investments'!$F28='My investments'!$H$15,$AA28,0))
A29: =IF('My investments'!$C29="Worth today",1,0) | B29: =IF('My investments'!$C29="Money in",1,0) | AA29: =IF('My investments'!$C29="Money in",'My investments'!$D29,0) | AB29: =IF('My investments'!$C29="Money out",'My investments'!$D29,0) | AC29: =IF('My investments'!$C29="Worth today",'My investments'!$D29,0) | AE29: =IF('My investments'!$H$11="",0,IF('My investments'!$F29='My investments'!$H$11,'My investments'!$E29,0)) | AF29: =IF('My investments'!$H$12="",0,IF('My investments'!$F29='My investments'!$H$12,'My investments'!$E29,0)) | AG29: =IF('My investments'!$H$13="",0,IF('My investments'!$F29='My investments'!$H$13,'My investments'!$E29,0)) | AH29: =IF('My investments'!$H$14="",0,IF('My investments'!$F29='My investments'!$H$14,'My investments'!$E29,0)) | AI29: =IF('My investments'!$H$15="",0,IF('My investments'!$F29='My investments'!$H$15,'My investments'!$E29,0)) | AK29: =IF('My investments'!$H$11="",0,IF('My investments'!$F29='My investments'!$H$11,$AA29,0)) | AL29: =IF('My investments'!$H$12="",0,IF('My investments'!$F29='My investments'!$H$12,$AA29,0)) | AM29: =IF('My investments'!$H$13="",0,IF('My investments'!$F29='My investments'!$H$13,$AA29,0)) | AN29: =IF('My investments'!$H$14="",0,IF('My investments'!$F29='My investments'!$H$14,$AA29,0)) | AO29: =IF('My investments'!$H$15="",0,IF('My investments'!$F29='My investments'!$H$15,$AA29,0))
A30: =IF('My investments'!$C30="Worth today",1,0) | B30: =IF('My investments'!$C30="Money in",1,0) | AA30: =IF('My investments'!$C30="Money in",'My investments'!$D30,0) | AB30: =IF('My investments'!$C30="Money out",'My investments'!$D30,0) | AC30: =IF('My investments'!$C30="Worth today",'My investments'!$D30,0) | AE30: =IF('My investments'!$H$11="",0,IF('My investments'!$F30='My investments'!$H$11,'My investments'!$E30,0)) | AF30: =IF('My investments'!$H$12="",0,IF('My investments'!$F30='My investments'!$H$12,'My investments'!$E30,0)) | AG30: =IF('My investments'!$H$13="",0,IF('My investments'!$F30='My investments'!$H$13,'My investments'!$E30,0)) | AH30: =IF('My investments'!$H$14="",0,IF('My investments'!$F30='My investments'!$H$14,'My investments'!$E30,0)) | AI30: =IF('My investments'!$H$15="",0,IF('My investments'!$F30='My investments'!$H$15,'My investments'!$E30,0)) | AK30: =IF('My investments'!$H$11="",0,IF('My investments'!$F30='My investments'!$H$11,$AA30,0)) | AL30: =IF('My investments'!$H$12="",0,IF('My investments'!$F30='My investments'!$H$12,$AA30,0)) | AM30: =IF('My investments'!$H$13="",0,IF('My investments'!$F30='My investments'!$H$13,$AA30,0)) | AN30: =IF('My investments'!$H$14="",0,IF('My investments'!$F30='My investments'!$H$14,$AA30,0)) | AO30: =IF('My investments'!$H$15="",0,IF('My investments'!$F30='My investments'!$H$15,$AA30,0))
A31: =IF('My investments'!$C31="Worth today",1,0) | B31: =IF('My investments'!$C31="Money in",1,0) | AA31: =IF('My investments'!$C31="Money in",'My investments'!$D31,0) | AB31: =IF('My investments'!$C31="Money out",'My investments'!$D31,0) | AC31: =IF('My investments'!$C31="Worth today",'My investments'!$D31,0) | AE31: =IF('My investments'!$H$11="",0,IF('My investments'!$F31='My investments'!$H$11,'My investments'!$E31,0)) | AF31: =IF('My investments'!$H$12="",0,IF('My investments'!$F31='My investments'!$H$12,'My investments'!$E31,0)) | AG31: =IF('My investments'!$H$13="",0,IF('My investments'!$F31='My investments'!$H$13,'My investments'!$E31,0)) | AH31: =IF('My investments'!$H$14="",0,IF('My investments'!$F31='My investments'!$H$14,'My investments'!$E31,0)) | AI31: =IF('My investments'!$H$15="",0,IF('My investments'!$F31='My investments'!$H$15,'My investments'!$E31,0)) | AK31: =IF('My investments'!$H$11="",0,IF('My investments'!$F31='My investments'!$H$11,$AA31,0)) | AL31: =IF('My investments'!$H$12="",0,IF('My investments'!$F31='My investments'!$H$12,$AA31,0)) | AM31: =IF('My investments'!$H$13="",0,IF('My investments'!$F31='My investments'!$H$13,$AA31,0)) | AN31: =IF('My investments'!$H$14="",0,IF('My investments'!$F31='My investments'!$H$14,$AA31,0)) | AO31: =IF('My investments'!$H$15="",0,IF('My investments'!$F31='My investments'!$H$15,$AA31,0))
A32: =IF('My investments'!$C32="Worth today",1,0) | B32: =IF('My investments'!$C32="Money in",1,0) | AA32: =IF('My investments'!$C32="Money in",'My investments'!$D32,0) | AB32: =IF('My investments'!$C32="Money out",'My investments'!$D32,0) | AC32: =IF('My investments'!$C32="Worth today",'My investments'!$D32,0) | AE32: =IF('My investments'!$H$11="",0,IF('My investments'!$F32='My investments'!$H$11,'My investments'!$E32,0)) | AF32: =IF('My investments'!$H$12="",0,IF('My investments'!$F32='My investments'!$H$12,'My investments'!$E32,0)) | AG32: =IF('My investments'!$H$13="",0,IF('My investments'!$F32='My investments'!$H$13,'My investments'!$E32,0)) | AH32: =IF('My investments'!$H$14="",0,IF('My investments'!$F32='My investments'!$H$14,'My investments'!$E32,0)) | AI32: =IF('My investments'!$H$15="",0,IF('My investments'!$F32='My investments'!$H$15,'My investments'!$E32,0)) | AK32: =IF('My investments'!$H$11="",0,IF('My investments'!$F32='My investments'!$H$11,$AA32,0)) | AL32: =IF('My investments'!$H$12="",0,IF('My investments'!$F32='My investments'!$H$12,$AA32,0)) | AM32: =IF('My investments'!$H$13="",0,IF('My investments'!$F32='My investments'!$H$13,$AA32,0)) | AN32: =IF('My investments'!$H$14="",0,IF('My investments'!$F32='My investments'!$H$14,$AA32,0)) | AO32: =IF('My investments'!$H$15="",0,IF('My investments'!$F32='My investments'!$H$15,$AA32,0))
... A507: =IF('My investments'!$C507="Worth today",1,0) | B507: =IF('My investments'!$C507="Money in",1,0) | AA507: =IF('My investments'!$C507="Money in",'My investments'!$D507,0) | AB507: =IF('My investments'!$C507="Money out",'My investments'!$D507,0) | AC507: =IF('My investments'!$C507="Worth today",'My investments'!$D507,0) | AE507: =IF('My investments'!$H$11="",0,IF('My investments'!$F507='My investments'!$H$11,'My investments'!$E507,0)) | AF507: =IF('My investments'!$H$12="",0,IF('My investments'!$F507='My investments'!$H$12,'My investments'!$E507,0)) | AG507: =IF('My investments'!$H$13="",0,IF('My investments'!$F507='My investments'!$H$13,'My investments'!$E507,0)) | AH507: =IF('My investments'!$H$14="",0,IF('My investments'!$F507='My investments'!$H$14,'My investments'!$E507,0)) | AI507: =IF('My investments'!$H$15="",0,IF('My investments'!$F507='My investments'!$H$15,'My investments'!$E507,0)) | AK507: =IF('My investments'!$H$11="",0,IF('My investments'!$F507='My investments'!$H$11,$AA507,0)) | AL507: =IF('My investments'!$H$12="",0,IF('My investments'!$F507='My investments'!$H$12,$AA507,0)) | AM507: =IF('My investments'!$H$13="",0,IF('My investments'!$F507='My investments'!$H$13,$AA507,0)) | AN507: =IF('My investments'!$H$14="",0,IF('My investments'!$F507='My investments'!$H$14,$AA507,0)) | AO507: =IF('My investments'!$H$15="",0,IF('My investments'!$F507='My investments'!$H$15,$AA507,0))
