Workbook
Name Flow_Dates: OFFSET('My investments'!$B$8,0,0,COUNT('My investments'!$B$8:$B$507),1)
Name Flow_Values: OFFSET('My investments'!$E$8,0,0,COUNT('My investments'!$B$8:$B$507),1)

Sheet Start here
B2: 1. This sheet works out your XIRR: the yearly rate the money you actually invested has earned.
B4: 2. Save your own copy before you type anything, so you always have a clean one.
B6: 3. On the My investments tab, enter one row for every payment you made: the date, then Investment or Withdrawal from the dropdown, then the amount as a plain positive number.
B8: 4. In the last row, enter today's date, choose Value today, and type what the holding is worth right now.
B10: 5. Your XIRR appears at the top of that tab. If it does not, read the line underneath it: it says what is still missing.
B12: 6. The Example tab is the same thing already filled in, if you get stuck.

Sheet My investments
A2: Fund name
A4: Your XIRR | B4: =IFERROR(XIRR(Flow_Values,Flow_Dates),IFERROR(XIRR(Flow_Values,Flow_Dates,-0.5),"Check the status line below"))
B5: =IF(COUNT($B$8:$B$507)=0,"Add your first investment above.",IF(Calc!$D$1=0,"Add a last row: today's date, Value today, and what the holding is worth now.",IF(Calc!$D$2=0,"Add at least one investment.","")))
B6: One row for every payment, with no blank rows in between. The last row must be today's date, Value today, and what the holding is worth now.
B7: Date | C7: What happened | D7: Amount | E7: Used by the sheet
E8: =IF($B8="","",IF($C8="Investment",-$D8,$D8))
E9: =IF($B9="","",IF($C9="Investment",-$D9,$D9))
E10: =IF($B10="","",IF($C10="Investment",-$D10,$D10))
E11: =IF($B11="","",IF($C11="Investment",-$D11,$D11))
E12: =IF($B12="","",IF($C12="Investment",-$D12,$D12))
E13: =IF($B13="","",IF($C13="Investment",-$D13,$D13))
E14: =IF($B14="","",IF($C14="Investment",-$D14,$D14))
E15: =IF($B15="","",IF($C15="Investment",-$D15,$D15))
E16: =IF($B16="","",IF($C16="Investment",-$D16,$D16))
E17: =IF($B17="","",IF($C17="Investment",-$D17,$D17))
E18: =IF($B18="","",IF($C18="Investment",-$D18,$D18))
E19: =IF($B19="","",IF($C19="Investment",-$D19,$D19))
... E507: =IF($B507="","",IF($C507="Investment",-$D507,$D507))

Sheet Example
A2: Fund name | B2: An example, already filled in
A4: Your XIRR | B4: =IFERROR(XIRR($E$8:$E$10,$B$8:$B$10),IFERROR(XIRR($E$8:$E$10,$B$8:$B$10,-0.5),"Check the status line below"))
B6: One row for every payment, with no blank rows in between. The last row must be today's date, Value today, and what the holding is worth now.
B7: Date | C7: What happened | D7: Amount | E7: Used by the sheet
B8: 45292 | C8: Investment | D8: 100000 | E8: =IF($B8="","",IF($C8="Investment",-$D8,$D8))
B9: 45658 | C9: Investment | D9: 100000 | E9: =IF($B9="","",IF($C9="Investment",-$D9,$D9))
B10: 46023 | C10: Value today | D10: 228000 | E10: =IF($B10="","",IF($C10="Investment",-$D10,$D10))
E11: =IF($B11="","",IF($C11="Investment",-$D11,$D11))
E12: =IF($B12="","",IF($C12="Investment",-$D12,$D12))
E13: =IF($B13="","",IF($C13="Investment",-$D13,$D13))
E14: =IF($B14="","",IF($C14="Investment",-$D14,$D14))
E15: =IF($B15="","",IF($C15="Investment",-$D15,$D15))
E16: =IF($B16="","",IF($C16="Investment",-$D16,$D16))
E17: =IF($B17="","",IF($C17="Investment",-$D17,$D17))
E18: =IF($B18="","",IF($C18="Investment",-$D18,$D18))
E19: =IF($B19="","",IF($C19="Investment",-$D19,$D19))
E20: =IF($B20="","",IF($C20="Investment",-$D20,$D20))
E21: =IF($B21="","",IF($C21="Investment",-$D21,$D21))
E22: =IF($B22="","",IF($C22="Investment",-$D22,$D22))
... E507: =IF($B507="","",IF($C507="Investment",-$D507,$D507))

Sheet About
B2: XIRR Calculator, version 1.0
B4: Built 15-Aug-2026
B6: This is an educational tool for readers. The figure it produces is before exit load and before tax, and it is not investment advice.
B8: Questions: use the channels listed in the book.
B10: The tabs are protected without a password. To adapt this sheet, choose Review, then Unprotect Sheet.
B12: No Excel? Upload this file to Google Sheets and it works there too, unchanged.

Sheet Calc
C1: Rows marked Value today | D1: =SUM($A$8:$A$507)
C2: Rows marked Investment | D2: =SUM($B$8:$B$507)
A8: =IF('My investments'!$C8="Value today",1,0) | B8: =IF('My investments'!$C8="Investment",1,0)
A9: =IF('My investments'!$C9="Value today",1,0) | B9: =IF('My investments'!$C9="Investment",1,0)
A10: =IF('My investments'!$C10="Value today",1,0) | B10: =IF('My investments'!$C10="Investment",1,0)
A11: =IF('My investments'!$C11="Value today",1,0) | B11: =IF('My investments'!$C11="Investment",1,0)
A12: =IF('My investments'!$C12="Value today",1,0) | B12: =IF('My investments'!$C12="Investment",1,0)
A13: =IF('My investments'!$C13="Value today",1,0) | B13: =IF('My investments'!$C13="Investment",1,0)
A14: =IF('My investments'!$C14="Value today",1,0) | B14: =IF('My investments'!$C14="Investment",1,0)
A15: =IF('My investments'!$C15="Value today",1,0) | B15: =IF('My investments'!$C15="Investment",1,0)
A16: =IF('My investments'!$C16="Value today",1,0) | B16: =IF('My investments'!$C16="Investment",1,0)
A17: =IF('My investments'!$C17="Value today",1,0) | B17: =IF('My investments'!$C17="Investment",1,0)
A18: =IF('My investments'!$C18="Value today",1,0) | B18: =IF('My investments'!$C18="Investment",1,0)
A19: =IF('My investments'!$C19="Value today",1,0) | B19: =IF('My investments'!$C19="Investment",1,0)
... A507: =IF('My investments'!$C507="Value today",1,0) | B507: =IF('My investments'!$C507="Investment",1,0)
